setup.py
bin/iot.py
iot/__init__.py
iot/pkg_info.py
iot.egg-info/PKG-INFO
iot.egg-info/SOURCES.txt
iot.egg-info/dependency_links.txt
iot.egg-info/top_level.txt
osiot/__init__.py
osiot/android/__init__.py
osiot/dashboard/__init__.py
osiot/hardware/__init__.py
osiot/python/__init__.py
osiot/python/get.py
osiot/python/iot.py
osiot/python/post.py
osiot/rest/__init__.py