Metadata-Version: 1.0
Name: iot
Version: 0.1.5
Summary: Open source Internet of Things
Home-page: http://www.phodal.com
Author: Phodal.Gmszone
Author-email: gmszone@gmail.com
License: GPL version 2
Platform: UNKNOWN
